src/alu.v
module alu(
    input [7:0] A,
    input [7:0] B,
    input [2:0] sel,
    output reg [7:0] Y
);

always @(*) begin
    case(sel)
        3'b000: Y = A + B;
        3'b001: Y = A - B;
        3'b010: Y = A & B;
        3'b011: Y = A | B;
        3'b100: Y = A ^ B;
        3'b101: Y = ~A;
        3'b110: Y = A + 1;
        3'b111: Y = A - 1;
    endcase
end

endmodule

alu_tb.v
module alu_tb;

reg [7:0] A, B;
reg [2:0] sel;
wire [7:0] Y;

alu uut (
    .A(A),
    .B(B),
    .sel(sel),
    .Y(Y)
);

initial begin
    A = 8'd10;
    B = 8'd5;

    sel = 3'b000; #10;
    sel = 3'b001; #10;
    sel = 3'b010; #10;
    sel = 3'b011; #10;
    sel = 3'b100; #10;
    sel = 3'b101; #10;
    sel = 3'b110; #10;
    sel = 3'b111; #10;

    $finish;
end

endmodule

simulation/alu.vcd
$date
	Tue Jun  9 13:51:36 2026
$end
$version
	Icarus Verilog
$end
$timescale
	1s
$end
$scope module alu_tb $end
$var wire 8 ! Y [7:0] $end
$var reg 8 " A [7:0] $end
$var reg 8 # B [7:0] $end
$var reg 3 $ sel [2:0] $end
$scope module uut $end
$var wire 8 % A [7:0] $end
$var wire 8 & B [7:0] $end
$var wire 3 ' sel [2:0] $end
$var reg 8 ( Y [7:0] $end
$upscope $end
$upscope $end
$enddefinitions $end
$comment Show the parameter values. $end
$dumpall
$end
#0
$dumpvars
b1111 (
b0 '
b101 &
b1010 %
b0 $
b101 #
b1010 "
b1111 !
$end
#10
b101 !
b101 (
b1 $
b1 '
#20
b0 !
b0 (
b10 $
b10 '
#30
b1111 !
b1111 (
b11 $
b11 '
#40
b100 $
b100 '
#50
b11110101 !
b11110101 (
b101 $
b101 '
#60
b1011 !
b1011 (
b110 $
b110 '
#70
b1001 !
b1001 (
b111 $
b111 '
